best/__init__.py
best/integration/__init__.py
best/unit/__init__.py
best/unit/conftest.py
best/unit/test_glue_session.py
best/unit/test_glue_session_demo.py
best/unit/test_session_apis.py
gsuite_grant_analyzer-0.7.8.dist-info/LICENSE.txt
gsuite_grant_analyzer-0.7.8.dist-info/METADATA
gsuite_grant_analyzer-0.7.8.dist-info/WHEEL
gsuite_grant_analyzer-0.7.8.dist-info/top_level.txt
gsuite_grant_analyzer-0.7.8.dist-info/RECORD
