Metadata-Version: 2.1
Name: gsuite-grant-analyzer
Version: 0.7.8
Summary: gsuite-grant-analyzer of gsuite-grant-analyzer of gsuite-grant-analyzer
Home-page: UNKNOWN
Author: Aloneee walker
Author-email: aloneewalker@facebook.com
License: UNKNOWN
Platform: UNKNOWN
Classifier: Programming Language :: Python :: 3
Classifier: License :: OSI Approved :: MIT License
Classifier: Operating System :: OS Independent
